LICENSE
README.md
setup.py
Findclone/__init__.py
Findclone/aiofindclone.py
Findclone/exceptions.py
Findclone/findclone.py
Findclone/models.py
Findclone/pillow_config.py
Findclone/utils.py
examples/example_async.py
examples/example_auth.py
examples/example_change_colours_and_font.py
examples/example_get_documentation.py
examples/example_interaction_with_objects.py
examples/example_upload_file.py
findclone_api.egg-info/PKG-INFO
findclone_api.egg-info/SOURCES.txt
findclone_api.egg-info/dependency_links.txt
findclone_api.egg-info/requires.txt
findclone_api.egg-info/top_level.txt