Metadata-Version: 2.1
Name: findclone-api
Version: 1.0.3.5
Summary: Unofficial Findclone API for humans
Home-page: https://github.com/vypivshiy
Author: Vypivshiy
License: MIT
Platform: UNKNOWN
Requires-Python: >=3.7
License-File: LICENSE
